chaosNLP/__init__.py
chaosNLP/seq2seq/__init__.py
chaosNLP/seq2seq/nmt.py
chaosNLP/seq2seq/seq2seq.starter.py
chaosNLP/transformers/__init__.py
chaosNLP/transformers/bert.py
chaosNLP/transformers/gpt1.py
chaosNLP/transformers/gpt2.py
chaosNLP/transformers/transformer.py
chaosNLP/utils/__init__.py
chaosNLP/utils/normalization.py
chaosNLP/utils/clustering/__init__.py
chaosNLP/utils/clustering/_single_pass_cluster.py
chaosNLP-0.0.1.dist-info/METADATA
chaosNLP-0.0.1.dist-info/WHEEL
chaosNLP-0.0.1.dist-info/top_level.txt
chaosNLP-0.0.1.dist-info/RECORD
