Metadata-Version: 2.1
Name: chaosNLP
Version: 0.0.1
Summary: 容易理解的NLP库
Author: huangchao
Author-email: huangchao.cpp@gmail.com
License: MIT License
Keywords: NLP
